Metadata-Version: 2.1
Name: py-workdocs-prep
Version: 0.4.0
Summary: AWS Workdocs Preparation Utility
Home-page: https://github.com/nicc777/py_workdocs_prep
Author: Nico Coetzee
Author-email: nicc777@gmail.com
License: UNKNOWN
Download-URL: https://github.com/nicc777/py_workdocs_prep/releases/download/release-0.4.0/py_workdocs_prep-0.4.0.tar.gz
Project-URL: Bug Reports, https://github.com/nicc777/py_workdocs_prep/issues
Project-URL: Source, https://github.com/nicc777/py_workdocs_prep
Keywords: aws workdocs
Platform: UNKNOWN
Classifier: Development Status :: 4 - Beta
Classifier: Intended Audience :: End Users/Desktop
Classifier: Environment :: Console
Classifier: Environment :: MacOS X
Classifier: Environment :: Win32 (MS Windows)
Classifier: Topic :: System :: Archiving
Classifier: Topic :: System :: Filesystems
Classifier: Topic :: Utilities
Classifier: License :: OSI Approved :: MIT License
Classifier: Programming Language :: Python :: 3.7
Classifier: Programming Language :: Python :: 3.8
Requires-Python: >=3.6, <4
Provides-Extra: test
Provides-Extra: dev
